edc_rest_api/__init__.py
edc_rest_api/add_custom_attributes.py
edc_rest_api/run_edc_lineage.py
edc_rest_api/run_edc_replication_lineage.py
edc_rest_api/edc_utilities/__init__.py
edc_rest_api/edc_utilities/edc_custom_attributes.py
edc_rest_api/edc_utilities/edc_lineage.py
edc_rest_api/edc_utilities/edc_replication_lineage.py
edc_rest_api/edc_utilities/edc_session_helper.py
edc_rest_api/edc_utilities/edcutils.py
edc_rest_api/edc_utilities/encodeUser.py
edc_rest_api/metadata_utilities/__init__.py
edc_rest_api/metadata_utilities/check_schema.py
edc_rest_api/metadata_utilities/generate_uuids.py
edc_rest_api/metadata_utilities/generic.py
edc_rest_api/metadata_utilities/generic_settings.py
edc_rest_api/metadata_utilities/json_file_utilities.py
edc_rest_api/metadata_utilities/load_custom_attributes.py
edc_rest_api/metadata_utilities/load_json_metadata.py
edc_rest_api/metadata_utilities/log_settings.py
edc_rest_api/metadata_utilities/messages.py
edc_rest_api/metadata_utilities/mu_logging.py
edc_rest_api/metadata_utilities/validate_schema.py
edc_rest_api/metadata_utilities/services/__init__.py
plugins/__init__.py
tests/__init__.py
tests/conftest.py
tests/test_add_custom_attributes.py
tests/test_run_edc_lineage.py
tests/edc_utilities/__init__.py
tests/edc_utilities/test_edc_custom_attributes.py
tests/edc_utilities/test_edc_lineage_formulas.py
tests/edc_utilities/test_edc_session_helper.py
tests/edc_utilities/test_edcutils.py
tests/fixtures/__init__.py
tests/fixtures/config_variations.py
tests/metadata_utilities/__init__.py
tests/metadata_utilities/test_generate_uuids.py
tests/metadata_utilities/test_load_custom_attributes.py
tests/metadata_utilities/test_log_settings.py
tests/metadata_utilities/test_validate_schema.py
informatica_edc_rest_api_samples-0.3.84.dist-info/METADATA
informatica_edc_rest_api_samples-0.3.84.dist-info/WHEEL
informatica_edc_rest_api_samples-0.3.84.dist-info/top_level.txt
informatica_edc_rest_api_samples-0.3.84.dist-info/RECORD
