Metadata-Version: 2.1
Name: informatica-edc-rest-api-samples
Version: 0.3.84
Summary: Examples how to use the Informatica EDC samples. Loosely based on Informatica's EDC-REST-API-Samples
Home-page: https://github.com/jacbeekers/Informatica-EDC-REST-API-Samples
Author: Jac. Beekers
Author-email: beekersjac@gmail.com
License: UNKNOWN
Platform: UNKNOWN
Classifier: Programming Language :: Python :: 3
Classifier: License :: OSI Approved :: MIT License
Classifier: Operating System :: OS Independent
Requires-Python: >=3.6
Requires-Dist: requests
Requires-Dist: urllib3
Requires-Dist: jinja2
Requires-Dist: opencensus-ext-azure
Requires-Dist: opencensus-ext-requests
Requires-Dist: jsonschema
